{
  "tool_name": "CSS Compatibility Checker",
  "tool_description": "Checks CSS properties and values for browser compatibility using known compatibility databases.",
  "parameters": {
    "css_properties": {
      "type": "array",
      "required": true,
      "items": {
        "type": "string"
      },
      "minItems": 1,
      "maxItems": 100,
      "description": "List of CSS properties to check compatibility for"
    },
    "target_browsers": {
      "type": "array",
      "required": true,
      "items": {
        "type": "string"
      },
      "description": "Target browsers in format 'browser_name version'"
    },
    "include_prefixes": {
      "type": "boolean",
      "required": false,
      "default": true,
      "description": "Whether to include vendor prefix suggestions"
    }
  },
  "error_messages": [
    "Invalid CSS property: One or more properties are not recognized CSS properties.",
    "Invalid browser format: Use format 'browser_name version' (e.g., 'chrome 90', 'firefox 88').",
    "Compatibility data unavailable: Unable to retrieve compatibility information.",
    "Unsupported browser: One or more specified browsers are not supported for compatibility checking."
  ],
  "usage": "Provide css_properties list and target_browsers to check compatibility, optionally include vendor prefix suggestions.",
  "output_details": {
    "compatible_properties": {
      "type": "array",
      "items": {
        "type": "string"
      },
      "description": "Properties supported across all target browsers"
    },
    "incompatible_properties": {
      "type": "array",
      "items": {
        "type": "string"
      },
      "description": "Properties with compatibility issues"
    },
    "prefix_suggestions": {
      "type": "array",
      "items": {
        "type": "string"
      },
      "description": "Vendor prefix suggestions for better compatibility"
    },
    "compatibility_score": {
      "type": "number",
      "description": "Overall compatibility score as percentage"
    }
  }
}