{
  "tool_name": "Onboarding Plan Creator",
  "tool_description": "Generates personalized onboarding plans for new volunteers based on their role, experience level, and organizational requirements.",
  "parameters": {
    "volunteer_id": {
      "type": "string",
      "required": true,
      "description": "ID of the volunteer to create onboarding plan for"
    },
    "assigned_role": {
      "type": "string",
      "required": true,
      "description": "Specific role assigned to the volunteer"
    },
    "experience_level": {
      "type": "string",
      "required": true,
      "description": "Volunteer's experience level: beginner, intermediate, advanced"
    },
    "available_hours": {
      "type": "integer",
      "required": true,
      "description": "Hours per week volunteer has available"
    },
    "start_date": {
      "type": "string",
      "required": true,
      "description": "Volunteer's intended start date",
      "format": "date-time"
    },
    "special_requirements": {
      "type": "array",
      "items": {
        "type": "string"
      },
      "required": false,
      "description": "Any special accommodations or requirements",
      "default": []
    },
    "mentor_assignment": {
      "type": "boolean",
      "required": false,
      "description": "Whether to assign a mentor",
      "default": true
    },
    "accelerated_track": {
      "type": "boolean",
      "required": false,
      "description": "Whether volunteer qualifies for accelerated onboarding",
      "default": false
    }
  },
  "error_messages": [
    "Invalid volunteer ID: Volunteer ID does not exist in the system.",
    "Invalid experience level: Experience level must be beginner, intermediate, or advanced.",
    "Invalid hours: Available hours must be between 1 and 40 per week.",
    "Invalid start date: Start date must be a future date in ISO 8601 format.",
    "Role not recognized: The assigned role is not in the organization's role database."
  ],
  "usage": "Provide volunteer ID, assigned role, experience level, available hours, and start date. Optionally specify special requirements, mentor assignment, and accelerated track eligibility.",
  "output_details": {
    "onboarding_plan_id": {
      "type": "string",
      "description": "Unique identifier for the onboarding plan"
    },
    "plan_duration_weeks": {
      "type": "integer",
      "description": "Expected duration of onboarding in weeks"
    },
    "milestone_dates": {
      "type": "array",
      "items": {
        "type": "string"
      },
      "description": "Key milestone dates throughout onboarding"
    },
    "required_trainings": {
      "type": "array",
      "items": {
        "type": "string"
      },
      "description": "List of required training modules"
    },
    "assigned_mentor_id": {
      "type": "string",
      "description": "ID of assigned mentor if mentor assignment is enabled"
    },
    "checklist_items": {
      "type": "array",
      "items": {
        "type": "string"
      },
      "description": "Checklist of onboarding tasks to complete"
    }
  }
}