{
  "tool_name": "Protocol Decoder",
  "tool_description": "Decodes structured communication protocols from demodulated signals to extract message content and metadata.",
  "parameters": {
    "data_file_id": {
      "type": "string",
      "required": true,
      "description": "Identifier of demodulated data file to decode"
    },
    "protocol_type": {
      "type": "string",
      "required": true,
      "description": "Communication protocol to decode"
    },
    "encoding_format": {
      "type": "string",
      "required": false,
      "description": "Data encoding format: ASCII, UTF-8, binary, hex",
      "default": "ASCII"
    }
  },
  "error_messages": [
    "Data file not accessible: The specified data_file_id cannot be found or opened",
    "Unsupported protocol: The specified protocol_type is not supported by this decoder",
    "Invalid encoding format: encoding_format must be one of [ASCII, UTF-8, binary, hex]",
    "Decoding failure: Unable to decode data due to corruption or incorrect protocol specification"
  ],
  "usage": "Specify data_file_id containing demodulated signal data, provide protocol_type for the communication standard used, and optionally set encoding_format for the data representation.",
  "output_details": {
    "decoded_messages": {
      "type": "array",
      "items": {
        "type": "string"
      },
      "description": "Array of successfully decoded message contents"
    },
    "message_timestamps": {
      "type": "array",
      "items": {
        "type": "string"
      },
      "description": "Timestamps for each decoded message"
    },
    "protocol_metadata": {
      "type": "string",
      "description": "JSON string containing protocol-specific metadata"
    },
    "decoding_confidence": {
      "type": "number",
      "description": "Confidence score for decoding accuracy (0-100)"
    }
  }
}