{
  "tool_name": "Reorder_Point_Calculator",
  "tool_description": "Calculates optimal reorder points considering demand forecasts, lead times, safety stock requirements, and inventory policy constraints.",
  "parameters": {
    "forecast_demand": {
      "type": "number",
      "required": true,
      "description": "Forecasted demand during lead time"
    },
    "safety_stock": {
      "type": "number",
      "required": true,
      "description": "Required safety stock level"
    },
    "lead_time_days": {
      "type": "number",
      "required": true,
      "description": "Expected lead time in days"
    },
    "review_period": {
      "type": "integer",
      "required": false,
      "description": "Inventory review period in days",
      "default": 1
    }
  },
  "error_messages": [
    "Invalid demand forecast: Must be a positive number",
    "Invalid safety stock: Must be non-negative",
    "Invalid lead time: Must be positive",
    "Invalid review period: Must be positive integer between 1 and 30"
  ],
  "usage": "Input forecast_demand, safety_stock, and lead_time_days. Adjust review_period for periodic review systems.",
  "output_details": {
    "reorder_point": {
      "type": "number",
      "description": "Calculated reorder point in units"
    },
    "buffer_coverage": {
      "type": "number",
      "description": "Days of demand coverage provided by reorder point"
    },
    "risk_assessment": {
      "type": "string",
      "description": "Risk level assessment: low, medium, high"
    }
  }
}