{
  "tool_name": "Service Quality Scorer",
  "tool_description": "Generates comprehensive service quality scores for carriers based on delivery performance, customer feedback, and service reliability metrics.",
  "parameters": {
    "delivery_analysis_id": {
      "type": "string",
      "required": true,
      "description": "Reference ID for delivery time analysis results"
    },
    "customer_feedback_source": {
      "type": "string",
      "required": true,
      "description": "Source of customer feedback data"
    },
    "scoring_weights": {
      "type": "array",
      "required": false,
      "description": "Weights for different quality factors (must sum to 100)",
      "items": {
        "type": "number"
      },
      "default": "None"
    },
    "quality_dimensions": {
      "type": "array",
      "required": false,
      "description": "Specific quality dimensions to evaluate",
      "items": {
        "type": "string"
      },
      "default": "None"
    },
    "minimum_feedback_count": {
      "type": "integer",
      "required": false,
      "description": "Minimum number of feedback entries required",
      "default": 5
    }
  },
  "error_messages": [
    "Invalid analysis reference: The delivery analysis ID cannot be found or has expired.",
    "Insufficient customer feedback: Not enough feedback data meets the minimum count requirement.",
    "Invalid scoring weights: Weights must be positive numbers that sum to 100.",
    "Invalid quality dimension: Supported dimensions include timeliness, packaging, communication, tracking, resolution.",
    "Feedback source unavailable: The specified customer feedback source is not accessible."
  ],
  "usage": "Provide delivery_analysis_id and customer_feedback_source. Optionally customize scoring_weights and quality_dimensions to focus on specific service aspects.",
  "output_details": {
    "overall_quality_scores": {
      "type": "array",
      "items": {
        "type": "number"
      },
      "description": "Overall quality scores by carrier (0-100 scale)"
    },
    "dimension_scores": {
      "type": "array",
      "items": {
        "type": "string"
      },
      "description": "Detailed scores for each quality dimension"
    },
    "quality_trends": {
      "type": "array",
      "items": {
        "type": "string"
      },
      "description": "Identified trends in service quality over time"
    }
  }
}