{
  "tool_name": "Category Mapping Generator",
  "tool_description": "Creates mapping rules between different taxonomy structures to enable category translation and data migration between classification systems.",
  "parameters": {
    "source_taxonomy_id": {
      "type": "string",
      "required": true,
      "description": "Identifier of the source taxonomy to map from"
    },
    "target_taxonomy_id": {
      "type": "string",
      "required": true,
      "description": "Identifier of the target taxonomy to map to"
    },
    "mapping_approach": {
      "type": "string",
      "required": false,
      "description": "Mapping generation approach: automatic, similarity_based, or keyword_matching",
      "default": "similarity_based"
    },
    "similarity_threshold": {
      "type": "number",
      "required": false,
      "description": "Minimum similarity score for automatic mappings (0.1-0.9)",
      "default": 0.7
    },
    "allow_many_to_one": {
      "type": "boolean",
      "required": false,
      "description": "Whether to allow multiple source categories to map to one target category",
      "default": true
    }
  },
  "error_messages": [
    "Invalid source taxonomy: The specified source taxonomy does not exist",
    "Invalid target taxonomy: The specified target taxonomy does not exist",
    "Invalid mapping approach: Use one of [automatic, similarity_based, keyword_matching]",
    "Invalid similarity threshold: Value must be between 0.1 and 0.9",
    "Mapping generation failed: Unable to generate meaningful mappings between taxonomies"
  ],
  "usage": "Provide source_taxonomy_id and target_taxonomy_id, optionally configure mapping_approach and parameters. The tool generates category mapping rules for taxonomy translation.",
  "output_details": {
    "mapping_summary": {
      "type": "string",
      "description": "Summary of mapping generation results"
    },
    "total_mappings": {
      "type": "integer",
      "description": "Total number of category mappings created"
    },
    "automatic_mappings": {
      "type": "integer",
      "description": "Number of mappings generated automatically"
    },
    "unmapped_categories": {
      "type": "integer",
      "description": "Number of source categories without mappings"
    },
    "confidence_distribution": {
      "type": "array",
      "items": {
        "type": "number"
      },
      "description": "Distribution of mapping confidence scores"
    },
    "mapping_coverage": {
      "type": "number",
      "description": "Percentage of source categories successfully mapped"
    }
  }
}