{
  "tool_name": "Response Template Manager",
  "tool_description": "Manages and retrieves appropriate response templates based on review sentiment, category, and business context to ensure consistent and relevant automated responses.",
  "parameters": {
    "sentiment": {
      "type": "string",
      "required": true,
      "description": "Primary sentiment of the review: positive, negative, or neutral"
    },
    "category": {
      "type": "string",
      "required": true,
      "description": "Review category such as product_quality, shipping, customer_service, pricing"
    },
    "business_type": {
      "type": "string",
      "required": false,
      "description": "Type of business: retail, service, restaurant, software, healthcare",
      "default": "retail"
    },
    "response_tone": {
      "type": "string",
      "required": false,
      "description": "Desired tone for response: professional, friendly, apologetic, grateful",
      "default": "professional"
    },
    "include_alternatives": {
      "type": "boolean",
      "required": false,
      "description": "Whether to return alternative template options",
      "default": false
    }
  },
  "error_messages": [
    "Invalid sentiment value: Use one of [positive, negative, neutral].",
    "Invalid business type: Use one of [retail, service, restaurant, software, healthcare].",
    "Invalid response tone: Use one of [professional, friendly, apologetic, grateful].",
    "No templates found: No matching templates exist for the specified sentiment and category combination."
  ],
  "usage": "Provide sentiment and category parameters from review analysis results. Optionally specify business_type and response_tone for more targeted templates. Set include_alternatives to true to get multiple template options.",
  "output_details": {
    "primary_template": {
      "type": "string",
      "description": "Main response template for the given parameters"
    },
    "alternative_templates": {
      "type": "array",
      "items": {
        "type": "string"
      },
      "description": "Alternative template options if requested"
    },
    "template_variables": {
      "type": "array",
      "items": {
        "type": "string"
      },
      "description": "Variable placeholders in the template that need customization"
    },
    "usage_guidelines": {
      "type": "string",
      "description": "Guidelines for using and customizing the template"
    }
  }
}