{
  "tool_name": "Inventory_Data_Fetcher",
  "tool_description": "Retrieves current inventory levels from specified warehouse systems or data sources, supporting multiple product SKUs and locations.",
  "parameters": {
    "source_system": {
      "type": "string",
      "required": true,
      "description": "The warehouse management system or data source identifier"
    },
    "sku_list": {
      "type": "array",
      "items": {
        "type": "string"
      },
      "required": true,
      "description": "List of product SKUs to retrieve inventory for",
      "minItems": 1,
      "maxItems": 1000
    },
    "location_ids": {
      "type": "array",
      "items": {
        "type": "string"
      },
      "required": false,
      "description": "Specific warehouse or location identifiers to query",
      "default": "None"
    }
  },
  "error_messages": [
    "Invalid source system: The specified source_system is not recognized or accessible.",
    "SKU not found: One or more SKUs in sku_list do not exist in the system.",
    "Location access denied: One or more location_ids are not accessible with current permissions.",
    "Connection timeout: Unable to connect to the source system within the timeout period.",
    "Rate limit exceeded: Too many requests made to the source system, please retry after delay."
  ],
  "usage": "Provide source_system and sku_list to retrieve inventory data. Optionally specify location_ids to limit the query scope. The tool returns current stock levels for each SKU-location combination.",
  "output_details": {
    "total_records": {
      "type": "integer",
      "description": "Number of inventory records retrieved"
    },
    "skus": {
      "type": "array",
      "items": {
        "type": "string"
      },
      "description": "List of SKUs for which data was retrieved"
    },
    "stock_levels": {
      "type": "array",
      "items": {
        "type": "integer"
      },
      "description": "Current stock quantities corresponding to each SKU"
    },
    "locations": {
      "type": "array",
      "items": {
        "type": "string"
      },
      "description": "Location identifiers for each inventory record"
    },
    "last_updated": {
      "type": "string",
      "description": "Timestamp when inventory data was last updated",
      "format": "date-time"
    }
  }
}