{
  "tool_name": "Date Parser Standardizer",
  "tool_description": "Parses and standardizes various historical date formats found in genealogical records, handling different calendar systems, abbreviations, and incomplete date information.",
  "parameters": {
    "date_strings": {
      "type": "array",
      "required": true,
      "description": "Array of date strings to parse and standardize"
    },
    "default_century": {
      "type": "integer",
      "required": false,
      "default": 1800,
      "description": "Default century for ambiguous two-digit years"
    },
    "calendar_system": {
      "type": "string",
      "required": false,
      "default": "gregorian",
      "description": "Calendar system: gregorian, julian, mixed"
    },
    "locale": {
      "type": "string",
      "required": false,
      "default": "en_US",
      "description": "Locale for date format interpretation"
    },
    "allow_approximate": {
      "type": "boolean",
      "required": false,
      "default": true,
      "description": "Whether to accept approximate dates (circa, about, etc.)"
    }
  },
  "error_messages": [
    "Empty date array: Provide at least one date string to parse",
    "Invalid default_century: Must be integer between 1000-2000",
    "Unsupported calendar_system: Use gregorian, julian, or mixed",
    "Invalid locale format: Use standard locale codes (e.g., en_US, en_GB)",
    "Date parsing failed: One or more dates could not be interpreted"
  ],
  "usage": "Input an array of date strings from historical documents. Configure parsing parameters for historical context. Returns standardized dates with confidence indicators.",
  "output_details": {
    "standardized_dates": {
      "type": "array",
      "items": {
        "type": "string"
      },
      "description": "Dates in ISO 8601 format (YYYY-MM-DD)"
    },
    "original_formats": {
      "type": "array",
      "items": {
        "type": "string"
      },
      "description": "Original date string formats"
    },
    "parsing_confidence": {
      "type": "array",
      "items": {
        "type": "number"
      },
      "description": "Confidence score for each parsed date"
    },
    "date_precision": {
      "type": "array",
      "items": {
        "type": "string"
      },
      "description": "Precision level: exact, year_month, year_only, approximate"
    },
    "parsing_notes": {
      "type": "array",
      "items": {
        "type": "string"
      },
      "description": "Notes about parsing decisions or ambiguities"
    }
  }
}