{
  "tool_name": "Experience Section Parser",
  "tool_description": "Parses work experience section to extract job titles, companies, employment dates, responsibilities, and achievements from resume text.",
  "parameters": {
    "resume_text": {
      "type": "string",
      "required": true,
      "description": "The full text content of the resume"
    },
    "include_internships": {
      "type": "boolean",
      "required": false,
      "description": "Include internship and co-op experiences",
      "default": true
    },
    "include_volunteer": {
      "type": "boolean",
      "required": false,
      "description": "Include volunteer work and unpaid positions",
      "default": false
    },
    "min_duration_months": {
      "type": "integer",
      "required": false,
      "description": "Minimum job duration in months to include",
      "default": 1
    },
    "extract_achievements": {
      "type": "boolean",
      "required": false,
      "description": "Extract quantified achievements and metrics",
      "default": true
    },
    "standardize_titles": {
      "type": "boolean",
      "required": false,
      "description": "Standardize job titles to common categories",
      "default": false
    }
  },
  "error_messages": [
    "Empty resume text: Provide non-empty resume_text content for processing.",
    "Invalid duration: min_duration_months must be a positive integer between 1 and 120.",
    "No experience section found: The resume may not contain a recognizable work experience section.",
    "Date parsing error: Unable to parse employment dates. Check date format consistency in the resume."
  ],
  "usage": "Provide resume_text and configure filtering options for internships, volunteer work, and minimum duration. Enable extract_achievements to capture quantified results and standardize_titles for consistent job categorization.",
  "output_details": {
    "positions": {
      "type": "array",
      "items": {
        "type": "string"
      },
      "description": "List of job positions with title, company, dates, and key responsibilities"
    },
    "companies": {
      "type": "array",
      "items": {
        "type": "string"
      },
      "description": "List of companies/organizations worked for"
    },
    "job_titles": {
      "type": "array",
      "items": {
        "type": "string"
      },
      "description": "List of job titles held"
    },
    "total_experience_years": {
      "type": "number",
      "description": "Total years of professional experience"
    },
    "achievements": {
      "type": "array",
      "items": {
        "type": "string"
      },
      "description": "Quantified achievements and accomplishments"
    },
    "employment_gaps": {
      "type": "array",
      "items": {
        "type": "string"
      },
      "description": "Identified gaps in employment history with duration"
    }
  }
}