{
  "tool_name": "Temporal Data Aligner",
  "tool_description": "Aligns and synchronizes population data from multiple years, handling changes in geographic boundaries and survey methodologies.",
  "parameters": {
    "data_years": {
      "type": "array",
      "required": true,
      "description": "Years of census data to align",
      "items": {
        "type": "integer"
      },
      "minItems": 2,
      "maxItems": 20
    },
    "alignment_method": {
      "type": "string",
      "required": false,
      "description": "Temporal alignment method: interpolation, boundary_adjustment, direct_comparison",
      "default": "boundary_adjustment"
    },
    "base_year": {
      "type": "integer",
      "required": false,
      "description": "Reference year for boundary definitions",
      "default": "None"
    },
    "handle_boundary_changes": {
      "type": "boolean",
      "required": false,
      "description": "Automatically handle geographic boundary changes between years",
      "default": true
    }
  },
  "error_messages": [
    "Insufficient years: Provide at least 2 years for temporal alignment",
    "Invalid alignment method: Use one of [interpolation, boundary_adjustment, direct_comparison]",
    "Base year not found: Specified base_year is not in the data_years array",
    "Temporal gaps too large: Years span too wide a range for reliable alignment",
    "Boundary data unavailable: Cannot perform boundary adjustment for specified years"
  ],
  "usage": "Provide data_years array with at least 2 years. Choose appropriate alignment_method based on analysis needs. Optionally specify base_year for consistent boundary definitions.",
  "output_details": {
    "aligned_years": {
      "type": "array",
      "items": {
        "type": "integer"
      },
      "description": "Years successfully aligned"
    },
    "alignment_summary": {
      "type": "string",
      "description": "Description of alignment process and adjustments made"
    },
    "boundary_adjustments": {
      "type": "integer",
      "description": "Number of geographic areas requiring boundary adjustments"
    },
    "temporal_consistency_score": {
      "type": "number",
      "description": "Data consistency score across years (0.0-1.0)"
    }
  }
}