{
  "tool_name": "Rating Filter",
  "tool_description": "Filters books based on reader ratings from various sources with configurable thresholds and rating sources.",
  "parameters": {
    "book_ids": {
      "type": "array",
      "required": true,
      "items": {
        "type": "string"
      },
      "description": "Array of book IDs to filter"
    },
    "min_rating": {
      "type": "number",
      "required": false,
      "default": null,
      "description": "Minimum average rating (0.0-5.0)"
    },
    "max_rating": {
      "type": "number",
      "required": false,
      "default": null,
      "description": "Maximum average rating (0.0-5.0)"
    },
    "rating_sources": {
      "type": "array",
      "required": false,
      "default": [
        "goodreads",
        "amazon",
        "libraryjournal"
      ],
      "items": {
        "type": "string"
      },
      "description": "Rating sources to consider"
    },
    "min_review_count": {
      "type": "integer",
      "required": false,
      "default": null,
      "description": "Minimum number of reviews required"
    },
    "rating_aggregation": {
      "type": "string",
      "required": false,
      "default": "average",
      "description": "How to aggregate ratings: average, weighted_average, or highest"
    }
  },
  "error_messages": [
    "Empty book_ids array: Provide at least one book ID to filter.",
    "Invalid rating range: min_rating and max_rating must be between 0.0 and 5.0.",
    "Invalid rating range: min_rating must be less than or equal to max_rating.",
    "Unknown rating source: One or more rating sources are not supported.",
    "Invalid aggregation method: Use one of [average, weighted_average, highest].",
    "Insufficient rating data: No books have enough ratings to meet the min_review_count threshold."
  ],
  "usage": "Provide book_ids array and rating criteria. Specify min_rating and/or max_rating to filter by rating thresholds. Use rating_sources to control which rating platforms to consider and min_review_count to ensure statistical significance.",
  "output_details": {
    "filtered_book_ids": {
      "type": "array",
      "items": {
        "type": "string"
      },
      "description": "Array of book IDs that meet the rating criteria"
    },
    "books_remaining": {
      "type": "integer",
      "description": "Number of books that passed the rating filter"
    },
    "average_rating": {
      "type": "number",
      "description": "Average rating of filtered books"
    },
    "rating_distribution": {
      "type": "array",
      "items": {
        "type": "integer"
      },
      "description": "Count of books in each rating bracket (1-star through 5-star)"
    },
    "sources_used": {
      "type": "array",
      "items": {
        "type": "string"
      },
      "description": "Rating sources that were successfully accessed and used"
    }
  }
}