{
  "tool_name": "Verse Context Analyzer",
  "tool_description": "Provides surrounding context for specific verses including chapter summaries and historical background.",
  "parameters": {
    "verse_reference": {
      "type": "string",
      "required": true,
      "description": "Specific verse or passage reference"
    },
    "tradition": {
      "type": "string",
      "required": true,
      "description": "Religious tradition"
    },
    "context_range": {
      "type": "integer",
      "required": false,
      "description": "Number of surrounding verses to include (1-10)",
      "default": 3
    }
  },
  "error_messages": [
    "Invalid verse reference: Provide a valid verse citation.",
    "Tradition not supported: Specify a recognized religious tradition.",
    "Context range invalid: Range must be between 1 and 10 verses."
  ],
  "usage": "Provide verse_reference and tradition; optionally set context_range. Returns the verse with surrounding context and background information.",
  "output_details": {
    "target_verse": {
      "type": "string",
      "description": "The requested verse text"
    },
    "surrounding_context": {
      "type": "string",
      "description": "Surrounding verses for context"
    },
    "chapter_summary": {
      "type": "string",
      "description": "Summary of the chapter containing the verse"
    },
    "historical_context": {
      "type": "string",
      "description": "Historical and cultural background"
    }
  }
}