{
  "tool_name": "Storage Space Analyzer",
  "tool_description": "Analyzes available storage space, calculates recording capacity, and provides recommendations for storage management.",
  "parameters": {
    "storage_path": {
      "type": "string",
      "required": true,
      "description": "File system path where recordings are stored"
    },
    "cleanup_older_than_days": {
      "type": "integer",
      "required": false,
      "default": 30,
      "description": "Consider files older than this many days for cleanup"
    }
  },
  "error_messages": [
    "Storage path not found: The specified storage path does not exist or is not accessible.",
    "Insufficient permissions: Cannot access storage location due to permission restrictions.",
    "Invalid cleanup period: Cleanup period must be between 1 and 365 days."
  ],
  "usage": "Provide the storage path where recordings are kept. Optionally specify cleanup period for old files analysis.",
  "output_details": {
    "total_space_gb": {
      "type": "number",
      "description": "Total storage space in gigabytes"
    },
    "used_space_gb": {
      "type": "number",
      "description": "Currently used storage space in gigabytes"
    },
    "available_space_gb": {
      "type": "number",
      "description": "Available storage space in gigabytes"
    },
    "recording_capacity_hours": {
      "type": "number",
      "description": "Estimated recording hours available with current settings"
    },
    "cleanup_candidates_count": {
      "type": "integer",
      "description": "Number of old files that could be cleaned up"
    },
    "cleanup_space_recoverable_gb": {
      "type": "number",
      "description": "Storage space that could be recovered by cleanup"
    }
  }
}