{
  "Tool Call": {
    "transformation_rules": [
      "type_conversion",
      "date_formatting",
      "null_handling",
      "string_cleanup",
      "numeric_rounding"
    ],
    "date_format": "MM/DD/YYYY",
    "null_replacement_strategy": "default",
    "numeric_precision": 3
  },
  "Return Data": {
    "rows_transformed": 1247,
    "transformations_applied": 6235,
    "null_values_handled": 89,
    "transformation_errors": [
      "Row 342: Invalid date format in field 'created_date'",
      "Row 758: Numeric conversion failed for field 'amount'"
    ]
  }
}