{
  "Tool Call": {
    "symbol": "AAPL",
    "rule_id": "RSI_OVERSOLD_ALERT",
    "market_data": [
      "175.50",
      "174.80",
      "176.20",
      "173.90",
      "175.10"
    ],
    "indicator_data": [
      "28.5",
      "27.8",
      "29.1"
    ],
    "force_generate": true
  },
  "Return Data": {
    "alert_generated": true,
    "alert_id": "ALERT_20241220_143052_RSI_OVERSOLD_AAPL",
    "alert_message": "OVERSOLD ALERT: AAPL RSI dropped to 27.8, below threshold of 30. Current price: $175.50",
    "priority": "HIGH",
    "timestamp": "2024-12-20T14:30:52Z",
    "conditions_met": [
      "RSI below 30",
      "Volume above average",
      "Price decline > 2%"
    ]
  }
}