{
  "Tool Call": {
    "patient_id": "PAT-7829",
    "medication_name": "Lisinopril",
    "dosage": "10mg",
    "frequency": "once daily",
    "route": "oral",
    "start_date": "2024-01-15T08:00:00Z",
    "prescriber_id": "DOC-4521",
    "indication": "hypertension",
    "quantity": 30,
    "refills": 5
  },
  "Return Data": {
    "medication_id": "MED-9847-2024",
    "drug_interactions": [
      "Potassium supplements - monitor serum potassium levels",
      "NSAIDs - may reduce antihypertensive effect"
    ],
    "allergy_alerts": [],
    "status": "active"
  }
}